mibandpreview/__init__.py
mibandpreview/__main__.py
mibandpreview/generator.py
mibandpreview/loader_miband4.py
mibandpreview/loader_miband5.py
mibandpreview/loader_miband6.py
mibandpreview/test.py
mibandpreview/tools.py
mibandpreview/res/mb6_mask.png
mibandpreview/res/mb6_mask_lite.png
mibandpreview_qt/__init__.py
mibandpreview_qt/__main__.py
mibandpreview_qt/app_info.py
mibandpreview_qt/main.py
mibandpreview_qt/mmk_updater.py
mibandpreview_qt/pref_storage.py
mibandpreview_qt/preview_thread.py
mibandpreview_qt/ui_adapter.py
mibandpreview_qt/ui_frames.py
mibandpreview_qt/update_checker.py
mibandpreview_qt/qt/app_ru.qm
mibandpreview_qt/res/error.png
mibandpreview_qt/res/icon48.png
mibandpreview_qt/res/icon96.png
mibandpreview_qt/res/mibandpreview-qt.png
mibandpreview_qt/res/no_file.png
mibandpreview-1.2.3.dist-info/LICENSE.txt
mibandpreview-1.2.3.dist-info/METADATA
mibandpreview-1.2.3.dist-info/WHEEL
mibandpreview-1.2.3.dist-info/top_level.txt
mibandpreview-1.2.3.dist-info/RECORD
