Metadata-Version: 2.1
Name: mibandpreview
Version: 1.2.3
Summary: Mi Band Preview
Home-page: https://github.com/melianmiko/mibandpreview
Download-URL: https://github.com/melianmiko/mibandpreview/archive/refs/tags/v1.2.3.tar.gz
Author: MelianMiko
Author-email: melianmiko@gmail.com
License: Apache 2.0
License-File: LICENSE.txt
Requires-Dist: Pillow
Provides-Extra: qt
Requires-Dist: PyQt5 ; extra == 'qt'
